qrcodeutil/__init__.py
qrcodeutil/reader.py
qrcodeutil-1.0.0.dist-info/METADATA
qrcodeutil-1.0.0.dist-info/WHEEL
qrcodeutil-1.0.0.dist-info/top_level.txt
qrcodeutil-1.0.0.dist-info/RECORD
